bringbuf/__init__.py
bringbuf/bringbuf.py
bringbuf-0.1.2.dist-info/DESCRIPTION.rst
bringbuf-0.1.2.dist-info/METADATA
bringbuf-0.1.2.dist-info/RECORD
bringbuf-0.1.2.dist-info/WHEEL
bringbuf-0.1.2.dist-info/metadata.json
bringbuf-0.1.2.dist-info/top_level.txt
