Metadata-Version: 2.0
Name: bringbuf
Version: 0.1.2
Summary: A simple circular buffer to handle byte streams (for instance from a serial port), heavily based on enque.
Home-page: http://github.com/ticktronaut/bringbuf
Author: Andreas Gschossmann
Author-email: ghandi_84@hotmail.com
License: MIT
Platform: UNKNOWN
